wonder_diffusion_sdk/__init__.py
wonder_diffusion_sdk/components/__init__.py
wonder_diffusion_sdk/components/deepcache.py
wonder_diffusion_sdk/components/dotdict.py
wonder_diffusion_sdk/components/lightning.py
wonder_diffusion_sdk/components/logger.py
wonder_diffusion_sdk/components/lora.py
wonder_diffusion_sdk/components/optimizations.py
wonder_diffusion_sdk/components/safety_checker.py
wonder_diffusion_sdk/config/__init__.py
wonder_diffusion_sdk/config/controlnet_config.py
wonder_diffusion_sdk/config/globals.py
wonder_diffusion_sdk/config/lora_config.py
wonder_diffusion_sdk/config/model_config.py
wonder_diffusion_sdk/config/scheduler_config.py
wonder_diffusion_sdk/config/sdk_config.py
wonder_diffusion_sdk/types/__init__.py
wonder_diffusion_sdk/types/controlnet_type.py
wonder_diffusion_sdk/types/controlnets.py
wonder_diffusion_sdk/types/pipeline_type.py
wonder_diffusion_sdk/types/pipelines.py
wonder_diffusion_sdk/types/scheduler_type.py
wonder_diffusion_sdk/types/schedulers.py
wonder_diffusion_sdk-0.0.7.dist-info/LICENCE
wonder_diffusion_sdk-0.0.7.dist-info/METADATA
wonder_diffusion_sdk-0.0.7.dist-info/WHEEL
wonder_diffusion_sdk-0.0.7.dist-info/top_level.txt
wonder_diffusion_sdk-0.0.7.dist-info/RECORD
