Metadata-Version: 2.1
Name: wonder-diffusion-sdk
Version: 0.0.7
Summary: Python SDK for common Wonder diffusion models
Author: basri
Author-email: basri@wonder.co
License-File: LICENCE
Requires-Dist: diffusers (==0.26.3)
